Guia_09/Guia_0900.v
// ---------------------------
// -- Clock generator
// ---------------------------
module clock (output clk);
    reg clk;
    
    initial begin
        clk = 1'b0;
    end
    
    always begin
        #12 clk = ~clk;
    end
endmodule

Guia_09/Guia_0903.v
`include "Guia_0900.v"

module pulse(output signal, input clock);
    reg [1:0] counter = 0; // Contador de 3 bits 
    reg signal;
    always @(posedge clock)
    begin
        if(counter < 2) signal = 1'b1; // Sinal alto para as primeiras 36 bordas positivas do relógio
        else signal = 1'b0;             // Sinal baixo para as próximas 36 bordas positivas
        if(counter == 2) counter = 0; // Reset contador depois de 72
        else counter = counter + 1;    // Incrementar contador
    end
endmodule

module Guia_0903;
    wire clk;
    clock clk_module(clk);
    wire pulse_signal;
    pulse pulse_module(pulse_signal, clk);
    
    initial
    begin
        $dumpfile("Guia_0903.vcd");
        $dumpvars(0, Guia_0903);
        #500 $finish;  // Simular por 500 unidades de tempo
    end
endmodule

Guia_09/Guia_0903.vcd
$date
	Sun Oct  1 13:45:48 2023
$end
$version
	Icarus Verilog
$end
$timescale
	1s
$end
$scope module Guia_0903 $end
$var wire 1 ! pulse_signal $end
$var wire 1 " clk $end
$scope module clk_module $end
$var reg 1 " clk $end
$upscope $end
$scope module pulse_module $end
$var wire 1 " clock $end
$var reg 2 # counter [1:0] $end
$var reg 1 ! signal $end
$upscope $end
$upscope $end
$enddefinitions $end
#0
$dumpvars
b0 #
0"
x!
$end
#12
b1 #
1!
1"
#24
0"
#36
b10 #
1"
#48
0"
#60
b0 #
0!
1"
#72
0"
#84
b1 #
1!
1"
#96
0"
#108
b10 #
1"
#120
0"
#132
b0 #
0!
1"
#144
0"
#156
b1 #
1!
1"
#168
0"
#180
b10 #
1"
#192
0"
#204
b0 #
0!
1"
#216
0"
#228
b1 #
1!
1"
#240
0"
#252
b10 #
1"
#264
0"
#276
b0 #
0!
1"
#288
0"
#300
b1 #
1!
1"
#312
0"
#324
b10 #
1"
#336
0"
#348
b0 #
0!
1"
#360
0"
#372
b1 #
1!
1"
#384
0"
#396
b10 #
1"
#408
0"
#420
b0 #
0!
1"
#432
0"
#444
b1 #
1!
1"
#456
0"
#468
b10 #
1"
#480
0"
#492
b0 #
0!
1"
